abap_converter/__init__.py
abap_converter/cli.py
abap_converter/converter.py
abap_converter/llm_providers/base.py
abap_converter/llm_providers/groq_provider.py
abap_converter/utils/file_detector.py
abap_converter-0.1.0.dist-info/METADATA
abap_converter-0.1.0.dist-info/WHEEL
abap_converter-0.1.0.dist-info/entry_points.txt
abap_converter-0.1.0.dist-info/top_level.txt
abap_converter-0.1.0.dist-info/RECORD
