Metadata-Version: 2.4
Name: abap-converter
Version: 0.1.0
Summary: Convert legacy ABAP to modern ABAP (7.5+) in-place via Groq LLM
Author-email: Sushruth Samson <samsushruth@gmail.com>, Neha <nehagoda02@gmail.com>
License: MIT
Requires-Python: >=3.9
Requires-Dist: groq>=0.26.0
Requires-Dist: python-dotenv>=1.1.0
